trtopicter
